src/lifx/auth.py
src/lifx/colors.py
src/lifx/effects.py
src/lifx/lifx.py
src/lifx/lights.py
src/lifx/scenes.py
lifx_cli-2.5.7.dist-info/METADATA
lifx_cli-2.5.7.dist-info/WHEEL
lifx_cli-2.5.7.dist-info/entry_points.txt
lifx_cli-2.5.7.dist-info/licenses/LICENSE
lifx_cli-2.5.7.dist-info/RECORD
