Metadata-Version: 2.1
Name: lifx-cli
Version: 2.5.7
Summary: The Unofficial LIFX CLI
Project-URL: Homepage, https://github.com/necrux/lifx-cli
Project-URL: Bug Tracker, https://github.com/necrux/lifx-cli/issues
Author-email: Wes Henderson <info@necrux.com>
License-File: LICENSE
Classifier: License :: OSI Approved :: MIT License
Classifier: Operating System :: OS Independent
Classifier: Programming Language :: Python :: 3
Classifier: Programming Language :: Python :: 3.5
Classifier: Programming Language :: Python :: 3.6
Classifier: Programming Language :: Python :: 3.7
Classifier: Programming Language :: Python :: 3.8
Classifier: Programming Language :: Python :: 3.9
Classifier: Programming Language :: Python :: 3.10
Classifier: Programming Language :: Python :: 3.11
Requires-Python: >=3.5
Requires-Dist: requests
Requires-Dist: tabulate
